README
rfc6266_parser.py
setup.py
test_rfc6266_parser.py
uc_rfc6266_parser.egg-info/PKG-INFO
uc_rfc6266_parser.egg-info/SOURCES.txt
uc_rfc6266_parser.egg-info/dependency_links.txt
uc_rfc6266_parser.egg-info/requires.txt
uc_rfc6266_parser.egg-info/top_level.txt