Metadata-Version: 2.1
Name: uc-rfc6266-parser
Version: 0.1.0
Summary: Fork of rfc6266 package with python 3.6+ support
Home-page: https://github.com/genme/python-rfc6266-parser
Author: Arseniy Baranov
Author-email: arseniy.baranov@gmail.com
License: GNU LGPL
Keywords: rfc6266 parser Content-Disposition http attachments
Platform: OS-independent
Classifier: Programming Language :: Python :: 3
Classifier: Programming Language :: Python :: Implementation :: CPython
Classifier: Programming Language :: Python :: Implementation :: PyPy
Classifier: Intended Audience :: Developers
Classifier: License :: OSI Approved :: GNU Library or Lesser General Public License (LGPL)
Classifier: Topic :: Internet :: WWW/HTTP
Provides-Extra: dev
